salamanderspace/FileIO.py
salamanderspace/Shocks.py
salamanderspace/Tables.py
salamanderspace/__init__.py
salamanderspace/vlm.py
salamanderspace/relations/__init__.py
salamanderspace/relations/dimensionless.py
salamanderspace/relations/isentropic.py
salamanderspace/relations/shockrelations.py
salamanderspace/relations/thermodynamic.py
salamanderspace-0.0.6.dist-info/METADATA
salamanderspace-0.0.6.dist-info/WHEEL
salamanderspace-0.0.6.dist-info/licenses/LICENSE
salamanderspace-0.0.6.dist-info/RECORD
